lonelypsc/client.py
lonelypsc/http_client.py
lonelypsc/py.typed
lonelypsc/ws_client.py
lonelypsc/config/config.py
lonelypsc/config/file_config.py
lonelypsc/config/http_config.py
lonelypsc/config/ws_config.py
lonelypsc/config/helpers/uvicorn_bind_config.py
lonelypsc/http/retrier.py
lonelypsc/http/notify/action.py
lonelypsc/http/notify/result.py
lonelypsc/types/sync_io.py
lonelypsc/types/websocket_message.py
lonelypsc/util/async_io.py
lonelypsc/util/errors.py
lonelypsc/util/io_helpers.py
lonelypsc/util/request_body_io.py
lonelypsc/ws/check_result.py
lonelypsc/ws/compressor.py
lonelypsc/ws/handle_connection_failure.py
lonelypsc/ws/internal_callbacks.py
lonelypsc/ws/state.py
lonelypsc/ws/websocket_connect_task.py
lonelypsc/ws/handlers/closing.py
lonelypsc/ws/handlers/configuring.py
lonelypsc/ws/handlers/connecting.py
lonelypsc/ws/handlers/handler.py
lonelypsc/ws/handlers/protocol.py
lonelypsc/ws/handlers/waiting_retry.py
lonelypsc/ws/handlers/open/check_backgrounded.py
lonelypsc/ws/handlers/open/check_management_tasks.py
lonelypsc/ws/handlers/open/check_read.py
lonelypsc/ws/handlers/open/check_receiving_authorizing.py
lonelypsc/ws/handlers/open/check_receiving_authorizing_missed.py
lonelypsc/ws/handlers/open/check_receiving_authorizing_simple.py
lonelypsc/ws/handlers/open/check_receiving_decompressing.py
lonelypsc/ws/handlers/open/check_receiving_waiting_compressor.py
lonelypsc/ws/handlers/open/check_resending_notifications.py
lonelypsc/ws/handlers/open/check_retry_tentative.py
lonelypsc/ws/handlers/open/check_send.py
lonelypsc/ws/handlers/open/check_sent_notifications.py
lonelypsc/ws/handlers/open/check_unsent_acks.py
lonelypsc/ws/handlers/open/check_unsent_notifications.py
lonelypsc/ws/handlers/open/cleanup.py
lonelypsc/ws/handlers/open/compressor_utils.py
lonelypsc/ws/handlers/open/handle_authorized_receive.py
lonelypsc/ws/handlers/open/handler.py
lonelypsc/ws/handlers/open/send_internal_message.py
lonelypsc/ws/handlers/open/wait_something_changed.py
lonelypsc-0.0.17.dist-info/LICENSE.md
lonelypsc-0.0.17.dist-info/METADATA
lonelypsc-0.0.17.dist-info/WHEEL
lonelypsc-0.0.17.dist-info/top_level.txt
lonelypsc-0.0.17.dist-info/RECORD
