Metadata-Version: 2.2
Name: lonelypsc
Version: 0.0.17
Summary: PubSub over HTTP (subscriber side)
Author-email: Timothy Moore <mtimothy984@gmail.com>
Classifier: Development Status :: 2 - Pre-Alpha
Classifier: Environment :: Web Environment
Classifier: Intended Audience :: Developers
Classifier: License :: OSI Approved :: MIT License
Classifier: Operating System :: OS Independent
Classifier: Programming Language :: Python :: 3
Classifier: Programming Language :: Python :: 3.9
Classifier: Programming Language :: Python :: 3.10
Classifier: Programming Language :: Python :: 3.11
Classifier: Programming Language :: Python :: 3.12
Classifier: Programming Language :: Python :: 3.13
License-File: LICENSE.md
Requires-Dist: fastapi>=0.115
Requires-Dist: aiohttp>=3.11
Requires-Dist: uvicorn>=0.32
Requires-Dist: lonelypsp>=0.0.46
Provides-Extra: standard
Requires-Dist: zstandard>=0.23; extra == "standard"
Requires-Dist: websockets>=14.1; extra == "standard"
